MANIFEST.in
README.md
requirements-dev.txt
requirements.txt
rsq
setup.cfg
setup.py
tests/test_rsq.py
traxix/__init__.py
traxix/rsq.py
traxix.rsq.egg-info/PKG-INFO
traxix.rsq.egg-info/SOURCES.txt
traxix.rsq.egg-info/dependency_links.txt
traxix.rsq.egg-info/requires.txt
traxix.rsq.egg-info/top_level.txt